{"index.md":"Cgb96qqp","readme.md":"CH6W0xY-","src_about_index.md":"D5pLvKL8","src_guide_ai.md":"C2wKEBKg","src_guide_cache.md":"BhqP_wiC","src_guide_controller.md":"DFXsvLef","src_guide_db.md":"JecGjjcC","src_guide_dev.md":"Cgkglw3x","src_guide_dir.md":"z6VUJtso","src_guide_exception.md":"DTaAZohQ","src_guide_flow.md":"CDskEDnP","src_guide_initdata.md":"D5kMLxxc","src_guide_plugin.md":"D4um12uG","src_guide_quick.md":"DbcQSNam","src_guide_security.md":"DjyHN9T3","src_guide_service.md":"Coeaaupo","src_guide_swagger.md":"C8SICQIq","src_guide_upload.md":"DSE1ASmj","src_introduce_index.md":"CqGpQfmF","src_introduce_show.md":"y18FuumV","src_introduce_src.md":"ByQ4FCeZ","src_question_common.md":"BDnOx12Z","src_todo_plan.md":"BzDFnPcU","src_todo_update.md":"BLutrh4G"}
